pysvn_util/__init__.py
pysvn_util/svn_util.py
pysvn_util-1.0.2.dist-info/LICENSE
pysvn_util-1.0.2.dist-info/METADATA
pysvn_util-1.0.2.dist-info/WHEEL
pysvn_util-1.0.2.dist-info/top_level.txt
pysvn_util-1.0.2.dist-info/zip-safe
pysvn_util-1.0.2.dist-info/RECORD
