Metadata-Version: 2.1
Name: pysvn_util
Version: 1.0.2
Summary: svn助手
Home-page: https://github.com/buyfakett
Author: buyfakett
Author-email: buyfakett@vip.qq.com
License: MIT
Requires-Python: >=3.6
License-File: LICENSE
